Metadata-Version: 2.1
Name: YaGPT
Version: 0.1.0
Summary: This Python library provides a simple wrapper for interacting with Yandex Language Models, making it easy to send requests for text generation.
Home-page: https://github.com/Artem174a/YaGPT_API_metods/
Author: Artem Mot
Author-email: artem174a@yandex.ru
Classifier: License :: OSI Approved :: MIT License
Classifier: Programming Language :: Python :: 3
Classifier: Programming Language :: Python :: 3.6
Classifier: Programming Language :: Python :: 3.7
Classifier: Programming Language :: Python :: 3.8
Classifier: Programming Language :: Python :: 3.9
Classifier: Programming Language :: Python :: 3.10
Classifier: Programming Language :: Python :: 3.11
License-File: LICENSE
